aioudp/__init__.py
aioudp/server.py
aio_udp_server-0.0.7.dist-info/LICENSE
aio_udp_server-0.0.7.dist-info/METADATA
aio_udp_server-0.0.7.dist-info/WHEEL
aio_udp_server-0.0.7.dist-info/top_level.txt
aio_udp_server-0.0.7.dist-info/zip-safe
aio_udp_server-0.0.7.dist-info/RECORD
