Metadata-Version: 2.1
Name: aio-udp-server
Version: 0.0.7
Summary: Asyncio UDP server with traffic throttling
Home-page: https://github.com/bashkirtsevich-llc/aioudp
Author: D.Bashkirtsevich
Author-email: bashkirtsevich@gmail.com
License: GPL3 License
Keywords: UDP asyncio UDPserver throttling throttler
Platform: UNKNOWN
Classifier: Programming Language :: Python
Requires-Python: >=3.6.*
License-File: LICENSE
